jokes/__init__.py
jokes/jokes.py
python_library_template-0.1.1.dist-info/METADATA
python_library_template-0.1.1.dist-info/WHEEL
python_library_template-0.1.1.dist-info/entry_points.txt
python_library_template-0.1.1.dist-info/top_level.txt
python_library_template-0.1.1.dist-info/RECORD
