Metadata-Version: 2.1
Name: python-library-template
Version: 0.1.1
Summary: Add your description here
Requires-Python: >=3.12
Requires-Dist: requests>=2.32.3
